ydnatl/__init__.py
ydnatl/core/__init__.py
ydnatl/core/element.py
ydnatl/core/factory.py
ydnatl/core/fragment.py
ydnatl/core/parser.py
ydnatl/styles/__init__.py
ydnatl/styles/style.py
ydnatl/styles/stylesheet.py
ydnatl/styles/theme.py
ydnatl/tags/__init__.py
ydnatl/tags/form.py
ydnatl/tags/html.py
ydnatl/tags/layout.py
ydnatl/tags/lists.py
ydnatl/tags/media.py
ydnatl/tags/table.py
ydnatl/tags/tag_factory.py
ydnatl/tags/text.py
ydnatl-1.0.9.dist-info/licenses/LICENSE
ydnatl-1.0.9.dist-info/METADATA
ydnatl-1.0.9.dist-info/WHEEL
ydnatl-1.0.9.dist-info/top_level.txt
ydnatl-1.0.9.dist-info/RECORD
