Metadata-Version: 2.4
Name: ydnatl
Version: 1.0.9
Summary: YDNATL is a Python library that lets you build HTML UI using simple Python classes.
Author-email: Sean Nieuwoudt <sean@underwulf.com>
Project-URL: Homepage, https://github.com/sn/ydnatl
Project-URL: Repository, https://github.com/sn/ydnatl
Project-URL: Issues, https://github.com/sn/ydnatl/issues
Classifier: Operating System :: OS Independent
Classifier: Intended Audience :: Developers
Classifier: License :: OSI Approved :: MIT License
Classifier: Programming Language :: Python :: 3
Classifier: Programming Language :: Python :: 3.8
Classifier: Programming Language :: Python :: 3.9
Classifier: Programming Language :: Python :: 3.10
Classifier: Programming Language :: Python :: 3.11
Classifier: Programming Language :: Python :: 3.12
Classifier: Programming Language :: Python :: 3.13
Classifier: Programming Language :: Python :: 3.14
Requires-Python: >=3.8
License-File: LICENSE
Provides-Extra: dev
Requires-Dist: build; extra == "dev"
Requires-Dist: twine; extra == "dev"
Requires-Dist: pytest; extra == "dev"
Requires-Dist: iniconfig; extra == "dev"
Requires-Dist: pluggy; extra == "dev"
Requires-Dist: packaging; extra == "dev"
Requires-Dist: black; extra == "dev"
Requires-Dist: flake8; extra == "dev"
Dynamic: license-file
